{
  "wideSmallMultiple": true,
  "title": "All full-time undergraduates",
  "series": "",
  "data": {
    "type": "bar",
    "columns": [
      [
        "",
        3900
      ]
    ],
    "labels": {
      "format": "dollar"
    }
  },
  "axis": {
    "rotated": true,
    "x": {
      "categories": "All full-time undergraduates",
      "type": "category"
    },
    "y": {
      "tick": {
        "format": "dollar",
        "count": 6
      },
      "max": 10000,
      "padding": {
        "top": 0,
        "bottom": 0
      }
    }
  },
  "metadata": {
    "source": "National Postsecondary Student Aid Study 2016",
    "notes": null
  }
}
